odoo10_addon_project_stage_closed-10.0.1.0.0-py2.7-nspkg.pth
odoo/addons/project_stage_closed/README.rst
odoo/addons/project_stage_closed/__init__.py
odoo/addons/project_stage_closed/__manifest__.py
odoo/addons/project_stage_closed/i18n/de.po
odoo/addons/project_stage_closed/i18n/es.po
odoo/addons/project_stage_closed/i18n/fi.po
odoo/addons/project_stage_closed/i18n/fr.po
odoo/addons/project_stage_closed/i18n/hr.po
odoo/addons/project_stage_closed/i18n/hu.po
odoo/addons/project_stage_closed/i18n/lv.po
odoo/addons/project_stage_closed/i18n/nb.po
odoo/addons/project_stage_closed/i18n/pt.po
odoo/addons/project_stage_closed/i18n/pt_BR.po
odoo/addons/project_stage_closed/i18n/pt_PT.po
odoo/addons/project_stage_closed/i18n/sl.po
odoo/addons/project_stage_closed/i18n/sv.po
odoo/addons/project_stage_closed/i18n/zh_CN.po
odoo/addons/project_stage_closed/models/__init__.py
odoo/addons/project_stage_closed/models/task_stage.py
odoo/addons/project_stage_closed/static/description/icon.png
odoo/addons/project_stage_closed/tests/__init__.py
odoo/addons/project_stage_closed/tests/test_project_stage_closed.py
odoo/addons/project_stage_closed/views/task_stage.xml
odoo10_addon_project_stage_closed-10.0.1.0.0.dist-info/DESCRIPTION.rst
odoo10_addon_project_stage_closed-10.0.1.0.0.dist-info/METADATA
odoo10_addon_project_stage_closed-10.0.1.0.0.dist-info/RECORD
odoo10_addon_project_stage_closed-10.0.1.0.0.dist-info/WHEEL
odoo10_addon_project_stage_closed-10.0.1.0.0.dist-info/metadata.json
odoo10_addon_project_stage_closed-10.0.1.0.0.dist-info/namespace_packages.txt
odoo10_addon_project_stage_closed-10.0.1.0.0.dist-info/top_level.txt
