Metadata-Version: 2.0
Name: odoo10-addon-project-stage-closed
Version: 10.0.1.0.0
Summary: Make the Closed flag on Task Stages available without installing sale_service
Home-page: http://acsone.eu
Author: ACSONE SA/NV,Tecnativa,Odoo Community Association (OCA)
Author-email: support@odoo-community.org
License: AGPL-3
Platform: UNKNOWN
Classifier: Programming Language :: Python :: 2.7
Classifier: Framework :: Odoo
Classifier: License :: OSI Approved :: GNU Affero General Public License v3
Requires-Dist: odoo (<10.1dev,>=10.0)
